genml/__init__.py
genml/genml.py
genml/mittag_leffler.py
genml-0.4.1.dist-info/LICENSE
genml-0.4.1.dist-info/METADATA
genml-0.4.1.dist-info/WHEEL
genml-0.4.1.dist-info/top_level.txt
genml-0.4.1.dist-info/RECORD
