Metadata-Version: 2.1
Name: genml
Version: 0.4.1
Summary: A Python package for generating Mittag-Leffler correlated noise
Home-page: UNKNOWN
License: UNKNOWN
Platform: UNKNOWN
Requires-Python: >=3.6
Requires-Dist: numpy (>=1.16.0)
Requires-Dist: tqdm (>=4.29.1)
Requires-Dist: scipy (>=1.2.0)
Requires-Dist: matplotlib (>=3.0.2)
Requires-Dist: multiprocess (>=0.70.12)
